{
  "data": [
    {
      "code": "NASDAQ",
      "currency": {
        "code": "USD",
        "name": "Dollar",
        "symbol": "$"
      },
      "timezone": "US/Eastern"
    },
    {
      "code": "AMEX",
      "currency": {
        "code": "USD",
        "name": "Dollar",
        "symbol": "$"
      },
      "timezone": "US/Eastern"
    },
    {
      "code": "LSE",
      "currency": {
        "code": "GBP",
        "name": "Pound",
        "symbol": "£"
      },
      "timezone": "Europe/London"
    },
    {
      "code": "SGX",
      "currency": {
        "code": "SGD",
        "name": "Dollar",
        "symbol": "$"
      },
      "timezone": "Asia/Singapore"
    },
    {
      "code": "ASX",
      "currency": {
        "code": "AUD",
        "name": "Dollar",
        "symbol": "$"
      },
      "timezone": "Australia/Sydney"
    },
    {
      "code": "NYSE",
      "currency": {
        "code": "USD",
        "name": "Dollar",
        "symbol": "$"
      },
      "timezone": "US/Eastern"
    },
    {
      "code": "NZX",
      "currency": {
        "code": "NZD",
        "name": "Dollar",
        "symbol": "$"
      },
      "timezone": "Pacific/Auckland"
    },
    {
      "code": "MOCK",
      "currency": {
        "code": "USD",
        "name": "Dollar",
        "symbol": "$"
      },
      "timezone": "UTC"
    }
  ]
}